tmux_mcp/__init__.py
tmux_mcp/server.py
tmux_sidecar-0.1.0.dist-info/METADATA
tmux_sidecar-0.1.0.dist-info/WHEEL
tmux_sidecar-0.1.0.dist-info/entry_points.txt
tmux_sidecar-0.1.0.dist-info/RECORD
