Metadata-Version: 2.4
Name: tmux-sidecar
Version: 0.1.0
Summary: A native Tmux MCP server for AI agents
Requires-Python: >=3.10
Requires-Dist: mcp
